SBCK/__AR2D2.py
SBCK/__CDFt.py
SBCK/__ECBC.py
SBCK/__IdBC.py
SBCK/__MBCn.py
SBCK/__MRec.py
SBCK/__OTC.py
SBCK/__QDM.py
SBCK/__QM.py
SBCK/__QMrs.py
SBCK/__R2D2.py
SBCK/__RBC.py
SBCK/__TSMBC.py
SBCK/__XClimPPP.py
SBCK/__dOTC.py
SBCK/__dTSMBC.py
SBCK/__init__.py
SBCK/__release.py
SBCK/datasets/__init__.py
SBCK/datasets/__multivariates.py
SBCK/datasets/__univariates.py
SBCK/metrics/__chebyshev.py
SBCK/metrics/__decorators.py
SBCK/metrics/__energy.py
SBCK/metrics/__entropy.py
SBCK/metrics/__euclidean.py
SBCK/metrics/__init__.py
SBCK/metrics/__manhattan.py
SBCK/metrics/__minkowski.py
SBCK/metrics/__wasserstein.py
SBCK/ppp/__PPPDiffRef.py
SBCK/ppp/__PPPExtremes.py
SBCK/ppp/__PPPLinkFunction.py
SBCK/ppp/__PPPNanValues.py
SBCK/ppp/__PPPOTCNoise.py
SBCK/ppp/__PPPSSR.py
SBCK/ppp/__PPPSys.py
SBCK/ppp/__PrePostProcessing.py
SBCK/ppp/__checkf.py
SBCK/ppp/__init__.py
SBCK/tools/__Dist.py
SBCK/tools/__OT.py
SBCK/tools/__Shift.py
SBCK/tools/__SlopeStoppingCriteria.py
SBCK/tools/__bin_width_estimator.py
SBCK/tools/__init__.py
SBCK/tools/__rv_extend.py
SBCK/tools/__shuffle.py
SBCK/tools/__tools_cpp.cpython-313-darwin.so
SBCK/tools/src/SparseHist.hpp
SBCK/tools/src/tools.cpp
sbck-1.4.2.dist-info/licenses/COPYING
sbck-1.4.2.dist-info/METADATA
sbck-1.4.2.dist-info/WHEEL
sbck-1.4.2.dist-info/top_level.txt
sbck-1.4.2.dist-info/RECORD
