Metadata-Version: 2.4
Name: SBCK
Version: 1.4.2
Author: Yoann Robin
Author-email: Yoann Robin <yoann.robin.k@gmail.com>
Maintainer-email: Yoann Robin <yoann.robin.k@gmail.com>
License-Expression: GPL-3.0-or-later
Platform: linux
Platform: macosx
Classifier: Development Status :: 5 - Production/Stable
Classifier: Natural Language :: English
Classifier: Operating System :: MacOS :: MacOS X
Classifier: Operating System :: POSIX :: Linux
Classifier: Programming Language :: Python :: 3
Classifier: Programming Language :: Python :: 3.10
Classifier: Programming Language :: Python :: 3.11
Classifier: Programming Language :: Python :: 3.12
Classifier: Programming Language :: Python :: 3.13
Classifier: Topic :: Scientific/Engineering :: Mathematics
Requires-Python: >=3.10
License-File: COPYING
Requires-Dist: numpy
Requires-Dist: scipy
Requires-Dist: pot>=0.9.0
Dynamic: author
Dynamic: license-file
Dynamic: platform
Dynamic: requires-python
